Spam_botz/Spam_botz.py
Spam_botz/__init__.py
Spam_botz/Modules/Numbers.py
Spam_botz/Modules/RageSpam.py
Spam_botz/Modules/RandNumbers.py
Spam_botz/Modules/RandomWords.py
Spam_botz/Modules/Spammer.py
Spam_botz/Modules/Static.py
Spam_botz/Modules/__init__.py
SpamBotz-1.0.0.dist-info/LICENSE
SpamBotz-1.0.0.dist-info/METADATA
SpamBotz-1.0.0.dist-info/WHEEL
SpamBotz-1.0.0.dist-info/top_level.txt
SpamBotz-1.0.0.dist-info/RECORD
