Metadata-Version: 2.1
Name: SpamBotz
Version: 1.0.0
Summary: A simple and easy to use Spam Bot
Home-page: http://www.vijaybalaji.social/Spam-Botz/
Author: S Vijay Balaji
Author-email: vijaybalajitheboss@gmail.com
License: UNKNOWN
Platform: UNKNOWN
Classifier: Programming Language :: Python :: 3
Classifier: License :: OSI Approved :: MIT License
Classifier: Operating System :: OS Independent
Requires-Python: >=3.6
